
{"items":[{"name":"Coree.NETASP.Extensions","href":"Coree.NETASP.Extensions.html","topicHref":"Coree.NETASP.Extensions.html","topicUid":"Coree.NETASP.Extensions","items":[{"name":"HttpResponseExtensions","href":"Coree.NETASP.Extensions.HttpResponseExtensions.html","topicHref":"Coree.NETASP.Extensions.HttpResponseExtensions.html","topicUid":"Coree.NETASP.Extensions.HttpResponseExtensions"}]},{"name":"Coree.NETASP.Extensions.KestrelOptions","href":"Coree.NETASP.Extensions.KestrelOptions.html","topicHref":"Coree.NETASP.Extensions.KestrelOptions.html","topicUid":"Coree.NETASP.Extensions.KestrelOptions","items":[{"name":"AuthenticationBuilderExtensions","href":"Coree.NETASP.Extensions.KestrelOptions.AuthenticationBuilderExtensions.html","topicHref":"Coree.NETASP.Extensions.KestrelOptions.AuthenticationBuilderExtensions.html","topicUid":"Coree.NETASP.Extensions.KestrelOptions.AuthenticationBuilderExtensions"},{"name":"ConfigureWebHostBuilderExtensions","href":"Coree.NETASP.Extensions.KestrelOptions.ConfigureWebHostBuilderExtensions.html","topicHref":"Coree.NETASP.Extensions.KestrelOptions.ConfigureWebHostBuilderExtensions.html","topicUid":"Coree.NETASP.Extensions.KestrelOptions.ConfigureWebHostBuilderExtensions"},{"name":"ConfigureWebHostBuilderExtensions.ListenType","href":"Coree.NETASP.Extensions.KestrelOptions.ConfigureWebHostBuilderExtensions.ListenType.html","topicHref":"Coree.NETASP.Extensions.KestrelOptions.ConfigureWebHostBuilderExtensions.ListenType.html","topicUid":"Coree.NETASP.Extensions.KestrelOptions.ConfigureWebHostBuilderExtensions.ListenType"},{"name":"xExtensions","href":"Coree.NETASP.Extensions.KestrelOptions.xExtensions.html","topicHref":"Coree.NETASP.Extensions.KestrelOptions.xExtensions.html","topicUid":"Coree.NETASP.Extensions.KestrelOptions.xExtensions"}]},{"name":"Coree.NETASP.Extensions.WebApplicationBuilderExtensions","href":"Coree.NETASP.Extensions.WebApplicationBuilderExtensions.html","topicHref":"Coree.NETASP.Extensions.WebApplicationBuilderExtensions.html","topicUid":"Coree.NETASP.Extensions.WebApplicationBuilderExtensions","items":[{"name":"WebAppBuilderExtensions","href":"Coree.NETASP.Extensions.WebApplicationBuilderExtensions.WebAppBuilderExtensions.html","topicHref":"Coree.NETASP.Extensions.WebApplicationBuilderExtensions.WebAppBuilderExtensions.html","topicUid":"Coree.NETASP.Extensions.WebApplicationBuilderExtensions.WebAppBuilderExtensions"},{"name":"WebApplicationBuilderExtension","href":"Coree.NETASP.Extensions.WebApplicationBuilderExtensions.WebApplicationBuilderExtension.html","topicHref":"Coree.NETASP.Extensions.WebApplicationBuilderExtensions.WebApplicationBuilderExtension.html","topicUid":"Coree.NETASP.Extensions.WebApplicationBuilderExtensions.WebApplicationBuilderExtension"}]},{"name":"Coree.NETASP.Middleware","href":"Coree.NETASP.Middleware.html","topicHref":"Coree.NETASP.Middleware.html","topicUid":"Coree.NETASP.Middleware","items":[{"name":"FailurePointsMiddleware","href":"Coree.NETASP.Middleware.FailurePointsMiddleware.html","topicHref":"Coree.NETASP.Middleware.FailurePointsMiddleware.html","topicUid":"Coree.NETASP.Middleware.FailurePointsMiddleware"},{"name":"FailurePointsMiddlewareExtensions","href":"Coree.NETASP.Middleware.FailurePointsMiddlewareExtensions.html","topicHref":"Coree.NETASP.Middleware.FailurePointsMiddlewareExtensions.html","topicUid":"Coree.NETASP.Middleware.FailurePointsMiddlewareExtensions"},{"name":"FailurePointsMiddlewareOptions","href":"Coree.NETASP.Middleware.FailurePointsMiddlewareOptions.html","topicHref":"Coree.NETASP.Middleware.FailurePointsMiddlewareOptions.html","topicUid":"Coree.NETASP.Middleware.FailurePointsMiddlewareOptions"},{"name":"RequestThrottlingMiddleware","href":"Coree.NETASP.Middleware.RequestThrottlingMiddleware.html","topicHref":"Coree.NETASP.Middleware.RequestThrottlingMiddleware.html","topicUid":"Coree.NETASP.Middleware.RequestThrottlingMiddleware"}]},{"name":"Coree.NETASP.Middleware.AcceptLanguageFiltering","href":"Coree.NETASP.Middleware.AcceptLanguageFiltering.html","topicHref":"Coree.NETASP.Middleware.AcceptLanguageFiltering.html","topicUid":"Coree.NETASP.Middleware.AcceptLanguageFiltering","items":[{"name":"AcceptLanguageFilteringExtensions","href":"Coree.NETASP.Middleware.AcceptLanguageFiltering.AcceptLanguageFilteringExtensions.html","topicHref":"Coree.NETASP.Middleware.AcceptLanguageFiltering.AcceptLanguageFilteringExtensions.html","topicUid":"Coree.NETASP.Middleware.AcceptLanguageFiltering.AcceptLanguageFilteringExtensions"},{"name":"AcceptLanguageFilteringMiddleware","href":"Coree.NETASP.Middleware.AcceptLanguageFiltering.AcceptLanguageFilteringMiddleware.html","topicHref":"Coree.NETASP.Middleware.AcceptLanguageFiltering.AcceptLanguageFilteringMiddleware.html","topicUid":"Coree.NETASP.Middleware.AcceptLanguageFiltering.AcceptLanguageFilteringMiddleware"},{"name":"AcceptLanguageFilteringOptions","href":"Coree.NETASP.Middleware.AcceptLanguageFiltering.AcceptLanguageFilteringOptions.html","topicHref":"Coree.NETASP.Middleware.AcceptLanguageFiltering.AcceptLanguageFilteringOptions.html","topicUid":"Coree.NETASP.Middleware.AcceptLanguageFiltering.AcceptLanguageFilteringOptions"}]},{"name":"Coree.NETASP.Middleware.DnsHostNameFiltering","href":"Coree.NETASP.Middleware.DnsHostNameFiltering.html","topicHref":"Coree.NETASP.Middleware.DnsHostNameFiltering.html","topicUid":"Coree.NETASP.Middleware.DnsHostNameFiltering","items":[{"name":"DnsHostNameFilteringMiddleware","href":"Coree.NETASP.Middleware.DnsHostNameFiltering.DnsHostNameFilteringMiddleware.html","topicHref":"Coree.NETASP.Middleware.DnsHostNameFiltering.DnsHostNameFilteringMiddleware.html","topicUid":"Coree.NETASP.Middleware.DnsHostNameFiltering.DnsHostNameFilteringMiddleware"},{"name":"DnsHostNameFilteringMiddlewareExtensions","href":"Coree.NETASP.Middleware.DnsHostNameFiltering.DnsHostNameFilteringMiddlewareExtensions.html","topicHref":"Coree.NETASP.Middleware.DnsHostNameFiltering.DnsHostNameFilteringMiddlewareExtensions.html","topicUid":"Coree.NETASP.Middleware.DnsHostNameFiltering.DnsHostNameFilteringMiddlewareExtensions"},{"name":"DnsHostNameFilteringOptions","href":"Coree.NETASP.Middleware.DnsHostNameFiltering.DnsHostNameFilteringOptions.html","topicHref":"Coree.NETASP.Middleware.DnsHostNameFiltering.DnsHostNameFilteringOptions.html","topicUid":"Coree.NETASP.Middleware.DnsHostNameFiltering.DnsHostNameFilteringOptions"}]},{"name":"Coree.NETASP.Middleware.HostNameFiltering","href":"Coree.NETASP.Middleware.HostNameFiltering.html","topicHref":"Coree.NETASP.Middleware.HostNameFiltering.html","topicUid":"Coree.NETASP.Middleware.HostNameFiltering","items":[{"name":"HostNameFilterOptions","href":"Coree.NETASP.Middleware.HostNameFiltering.HostNameFilterOptions.html","topicHref":"Coree.NETASP.Middleware.HostNameFiltering.HostNameFilterOptions.html","topicUid":"Coree.NETASP.Middleware.HostNameFiltering.HostNameFilterOptions"},{"name":"HostNameFilteringExtensions","href":"Coree.NETASP.Middleware.HostNameFiltering.HostNameFilteringExtensions.html","topicHref":"Coree.NETASP.Middleware.HostNameFiltering.HostNameFilteringExtensions.html","topicUid":"Coree.NETASP.Middleware.HostNameFiltering.HostNameFilteringExtensions"},{"name":"HostNameFilteringMiddleware","href":"Coree.NETASP.Middleware.HostNameFiltering.HostNameFilteringMiddleware.html","topicHref":"Coree.NETASP.Middleware.HostNameFiltering.HostNameFilteringMiddleware.html","topicUid":"Coree.NETASP.Middleware.HostNameFiltering.HostNameFilteringMiddleware"}]},{"name":"Coree.NETASP.Middleware.NewFolder","href":"Coree.NETASP.Middleware.NewFolder.html","topicHref":"Coree.NETASP.Middleware.NewFolder.html","topicUid":"Coree.NETASP.Middleware.NewFolder","items":[{"name":"PreMiddlewareHostedService","href":"Coree.NETASP.Middleware.NewFolder.PreMiddlewareHostedService.html","topicHref":"Coree.NETASP.Middleware.NewFolder.PreMiddlewareHostedService.html","topicUid":"Coree.NETASP.Middleware.NewFolder.PreMiddlewareHostedService"},{"name":"WaitForPreMiddlewareHostedServiceMiddleware","href":"Coree.NETASP.Middleware.NewFolder.WaitForPreMiddlewareHostedServiceMiddleware.html","topicHref":"Coree.NETASP.Middleware.NewFolder.WaitForPreMiddlewareHostedServiceMiddleware.html","topicUid":"Coree.NETASP.Middleware.NewFolder.WaitForPreMiddlewareHostedServiceMiddleware"},{"name":"fooExtensions","href":"Coree.NETASP.Middleware.NewFolder.fooExtensions.html","topicHref":"Coree.NETASP.Middleware.NewFolder.fooExtensions.html","topicUid":"Coree.NETASP.Middleware.NewFolder.fooExtensions"}]},{"name":"Coree.NETASP.Middleware.PathDeep","href":"Coree.NETASP.Middleware.PathDeep.html","topicHref":"Coree.NETASP.Middleware.PathDeep.html","topicUid":"Coree.NETASP.Middleware.PathDeep","items":[{"name":"PathDeepFilteringExtensions","href":"Coree.NETASP.Middleware.PathDeep.PathDeepFilteringExtensions.html","topicHref":"Coree.NETASP.Middleware.PathDeep.PathDeepFilteringExtensions.html","topicUid":"Coree.NETASP.Middleware.PathDeep.PathDeepFilteringExtensions"},{"name":"PathDeepFilteringMiddleware","href":"Coree.NETASP.Middleware.PathDeep.PathDeepFilteringMiddleware.html","topicHref":"Coree.NETASP.Middleware.PathDeep.PathDeepFilteringMiddleware.html","topicUid":"Coree.NETASP.Middleware.PathDeep.PathDeepFilteringMiddleware"},{"name":"PathDeepFilteringOptions","href":"Coree.NETASP.Middleware.PathDeep.PathDeepFilteringOptions.html","topicHref":"Coree.NETASP.Middleware.PathDeep.PathDeepFilteringOptions.html","topicUid":"Coree.NETASP.Middleware.PathDeep.PathDeepFilteringOptions"}]},{"name":"Coree.NETASP.Middleware.ProtocolFiltering","href":"Coree.NETASP.Middleware.ProtocolFiltering.html","topicHref":"Coree.NETASP.Middleware.ProtocolFiltering.html","topicUid":"Coree.NETASP.Middleware.ProtocolFiltering","items":[{"name":"ProtocolFilteringMiddleware","href":"Coree.NETASP.Middleware.ProtocolFiltering.ProtocolFilteringMiddleware.html","topicHref":"Coree.NETASP.Middleware.ProtocolFiltering.ProtocolFilteringMiddleware.html","topicUid":"Coree.NETASP.Middleware.ProtocolFiltering.ProtocolFilteringMiddleware"},{"name":"ProtocolFilteringMiddlewareExtensions","href":"Coree.NETASP.Middleware.ProtocolFiltering.ProtocolFilteringMiddlewareExtensions.html","topicHref":"Coree.NETASP.Middleware.ProtocolFiltering.ProtocolFilteringMiddlewareExtensions.html","topicUid":"Coree.NETASP.Middleware.ProtocolFiltering.ProtocolFilteringMiddlewareExtensions"},{"name":"ProtocolFilteringOptions","href":"Coree.NETASP.Middleware.ProtocolFiltering.ProtocolFilteringOptions.html","topicHref":"Coree.NETASP.Middleware.ProtocolFiltering.ProtocolFilteringOptions.html","topicUid":"Coree.NETASP.Middleware.ProtocolFiltering.ProtocolFilteringOptions"}]},{"name":"Coree.NETASP.Middleware.RequestLogging","href":"Coree.NETASP.Middleware.RequestLogging.html","topicHref":"Coree.NETASP.Middleware.RequestLogging.html","topicUid":"Coree.NETASP.Middleware.RequestLogging","items":[{"name":"RequestLoggingMiddleware","href":"Coree.NETASP.Middleware.RequestLogging.RequestLoggingMiddleware.html","topicHref":"Coree.NETASP.Middleware.RequestLogging.RequestLoggingMiddleware.html","topicUid":"Coree.NETASP.Middleware.RequestLogging.RequestLoggingMiddleware"}]},{"name":"Coree.NETASP.Middleware.RequestUrlFiltering","href":"Coree.NETASP.Middleware.RequestUrlFiltering.html","topicHref":"Coree.NETASP.Middleware.RequestUrlFiltering.html","topicUid":"Coree.NETASP.Middleware.RequestUrlFiltering","items":[{"name":"RequestUrlFilteringExtensions","href":"Coree.NETASP.Middleware.RequestUrlFiltering.RequestUrlFilteringExtensions.html","topicHref":"Coree.NETASP.Middleware.RequestUrlFiltering.RequestUrlFilteringExtensions.html","topicUid":"Coree.NETASP.Middleware.RequestUrlFiltering.RequestUrlFilteringExtensions"},{"name":"RequestUrlFilteringMiddleware","href":"Coree.NETASP.Middleware.RequestUrlFiltering.RequestUrlFilteringMiddleware.html","topicHref":"Coree.NETASP.Middleware.RequestUrlFiltering.RequestUrlFilteringMiddleware.html","topicUid":"Coree.NETASP.Middleware.RequestUrlFiltering.RequestUrlFilteringMiddleware"},{"name":"RequestUrlFilteringOptions","href":"Coree.NETASP.Middleware.RequestUrlFiltering.RequestUrlFilteringOptions.html","topicHref":"Coree.NETASP.Middleware.RequestUrlFiltering.RequestUrlFilteringOptions.html","topicUid":"Coree.NETASP.Middleware.RequestUrlFiltering.RequestUrlFilteringOptions"}]},{"name":"Coree.NETASP.Middleware.ResponseRecording","href":"Coree.NETASP.Middleware.ResponseRecording.html","topicHref":"Coree.NETASP.Middleware.ResponseRecording.html","topicUid":"Coree.NETASP.Middleware.ResponseRecording","items":[{"name":"ResponseRecordingMiddleware","href":"Coree.NETASP.Middleware.ResponseRecording.ResponseRecordingMiddleware.html","topicHref":"Coree.NETASP.Middleware.ResponseRecording.ResponseRecordingMiddleware.html","topicUid":"Coree.NETASP.Middleware.ResponseRecording.ResponseRecordingMiddleware"}]},{"name":"Coree.NETASP.Middleware.SegmentBlacklistFiltering","href":"Coree.NETASP.Middleware.SegmentBlacklistFiltering.html","topicHref":"Coree.NETASP.Middleware.SegmentBlacklistFiltering.html","topicUid":"Coree.NETASP.Middleware.SegmentBlacklistFiltering","items":[{"name":"SegmentBlacklistFilterOptions","href":"Coree.NETASP.Middleware.SegmentBlacklistFiltering.SegmentBlacklistFilterOptions.html","topicHref":"Coree.NETASP.Middleware.SegmentBlacklistFiltering.SegmentBlacklistFilterOptions.html","topicUid":"Coree.NETASP.Middleware.SegmentBlacklistFiltering.SegmentBlacklistFilterOptions"},{"name":"SegmentBlacklistFilteringExtensions","href":"Coree.NETASP.Middleware.SegmentBlacklistFiltering.SegmentBlacklistFilteringExtensions.html","topicHref":"Coree.NETASP.Middleware.SegmentBlacklistFiltering.SegmentBlacklistFilteringExtensions.html","topicUid":"Coree.NETASP.Middleware.SegmentBlacklistFiltering.SegmentBlacklistFilteringExtensions"},{"name":"SegmentBlacklistFilteringMiddleware","href":"Coree.NETASP.Middleware.SegmentBlacklistFiltering.SegmentBlacklistFilteringMiddleware.html","topicHref":"Coree.NETASP.Middleware.SegmentBlacklistFiltering.SegmentBlacklistFilteringMiddleware.html","topicUid":"Coree.NETASP.Middleware.SegmentBlacklistFiltering.SegmentBlacklistFilteringMiddleware"}]},{"name":"Coree.NETASP.Middleware.UnwantedHeaderKeysFiltering","href":"Coree.NETASP.Middleware.UnwantedHeaderKeysFiltering.html","topicHref":"Coree.NETASP.Middleware.UnwantedHeaderKeysFiltering.html","topicUid":"Coree.NETASP.Middleware.UnwantedHeaderKeysFiltering","items":[{"name":"UnwantedHeaderKeysMiddleware","href":"Coree.NETASP.Middleware.UnwantedHeaderKeysFiltering.UnwantedHeaderKeysMiddleware.html","topicHref":"Coree.NETASP.Middleware.UnwantedHeaderKeysFiltering.UnwantedHeaderKeysMiddleware.html","topicUid":"Coree.NETASP.Middleware.UnwantedHeaderKeysFiltering.UnwantedHeaderKeysMiddleware"},{"name":"UnwantedHeaderKeysMiddlewareExtensions","href":"Coree.NETASP.Middleware.UnwantedHeaderKeysFiltering.UnwantedHeaderKeysMiddlewareExtensions.html","topicHref":"Coree.NETASP.Middleware.UnwantedHeaderKeysFiltering.UnwantedHeaderKeysMiddlewareExtensions.html","topicUid":"Coree.NETASP.Middleware.UnwantedHeaderKeysFiltering.UnwantedHeaderKeysMiddlewareExtensions"},{"name":"UnwantedHeaderKeysOptions","href":"Coree.NETASP.Middleware.UnwantedHeaderKeysFiltering.UnwantedHeaderKeysOptions.html","topicHref":"Coree.NETASP.Middleware.UnwantedHeaderKeysFiltering.UnwantedHeaderKeysOptions.html","topicUid":"Coree.NETASP.Middleware.UnwantedHeaderKeysFiltering.UnwantedHeaderKeysOptions"}]},{"name":"Coree.NETASP.Middleware.UserAgentFiltering","href":"Coree.NETASP.Middleware.UserAgentFiltering.html","topicHref":"Coree.NETASP.Middleware.UserAgentFiltering.html","topicUid":"Coree.NETASP.Middleware.UserAgentFiltering","items":[{"name":"UserAgentFilterOptions","href":"Coree.NETASP.Middleware.UserAgentFiltering.UserAgentFilterOptions.html","topicHref":"Coree.NETASP.Middleware.UserAgentFiltering.UserAgentFilterOptions.html","topicUid":"Coree.NETASP.Middleware.UserAgentFiltering.UserAgentFilterOptions"},{"name":"UserAgentFilteringExtensions","href":"Coree.NETASP.Middleware.UserAgentFiltering.UserAgentFilteringExtensions.html","topicHref":"Coree.NETASP.Middleware.UserAgentFiltering.UserAgentFilteringExtensions.html","topicUid":"Coree.NETASP.Middleware.UserAgentFiltering.UserAgentFilteringExtensions"},{"name":"UserAgentFilteringMiddleware","href":"Coree.NETASP.Middleware.UserAgentFiltering.UserAgentFilteringMiddleware.html","topicHref":"Coree.NETASP.Middleware.UserAgentFiltering.UserAgentFilteringMiddleware.html","topicUid":"Coree.NETASP.Middleware.UserAgentFiltering.UserAgentFilteringMiddleware"}]},{"name":"Coree.NETASP.Services.CertificateManager","href":"Coree.NETASP.Services.CertificateManager.html","topicHref":"Coree.NETASP.Services.CertificateManager.html","topicUid":"Coree.NETASP.Services.CertificateManager","items":[{"name":"CertificateManager","href":"Coree.NETASP.Services.CertificateManager.CertificateManager.html","topicHref":"Coree.NETASP.Services.CertificateManager.CertificateManager.html","topicUid":"Coree.NETASP.Services.CertificateManager.CertificateManager"},{"name":"CertificateManagerService","href":"Coree.NETASP.Services.CertificateManager.CertificateManagerService.html","topicHref":"Coree.NETASP.Services.CertificateManager.CertificateManagerService.html","topicUid":"Coree.NETASP.Services.CertificateManager.CertificateManagerService"},{"name":"CommonDistinguishedNameBuilder","href":"Coree.NETASP.Services.CertificateManager.CommonDistinguishedNameBuilder.html","topicHref":"Coree.NETASP.Services.CertificateManager.CommonDistinguishedNameBuilder.html","topicUid":"Coree.NETASP.Services.CertificateManager.CommonDistinguishedNameBuilder"},{"name":"DistinguishedName","href":"Coree.NETASP.Services.CertificateManager.DistinguishedName.html","topicHref":"Coree.NETASP.Services.CertificateManager.DistinguishedName.html","topicUid":"Coree.NETASP.Services.CertificateManager.DistinguishedName"},{"name":"ICertificateManagerService","href":"Coree.NETASP.Services.CertificateManager.ICertificateManagerService.html","topicHref":"Coree.NETASP.Services.CertificateManager.ICertificateManagerService.html","topicUid":"Coree.NETASP.Services.CertificateManager.ICertificateManagerService"}]},{"name":"Coree.NETASP.Services.CookieAuth","href":"Coree.NETASP.Services.CookieAuth.html","topicHref":"Coree.NETASP.Services.CookieAuth.html","topicUid":"Coree.NETASP.Services.CookieAuth","items":[{"name":"AuthExtensions","href":"Coree.NETASP.Services.CookieAuth.AuthExtensions.html","topicHref":"Coree.NETASP.Services.CookieAuth.AuthExtensions.html","topicUid":"Coree.NETASP.Services.CookieAuth.AuthExtensions"},{"name":"CookieAuthHandler","href":"Coree.NETASP.Services.CookieAuth.CookieAuthHandler.html","topicHref":"Coree.NETASP.Services.CookieAuth.CookieAuthHandler.html","topicUid":"Coree.NETASP.Services.CookieAuth.CookieAuthHandler"},{"name":"ICookieAuthHandler","href":"Coree.NETASP.Services.CookieAuth.ICookieAuthHandler.html","topicHref":"Coree.NETASP.Services.CookieAuth.ICookieAuthHandler.html","topicUid":"Coree.NETASP.Services.CookieAuth.ICookieAuthHandler"}]},{"name":"Coree.NETASP.Services.Instancer","href":"Coree.NETASP.Services.Instancer.html","topicHref":"Coree.NETASP.Services.Instancer.html","topicUid":"Coree.NETASP.Services.Instancer","items":[{"name":"IServerConfigurationAnalyzer","href":"Coree.NETASP.Services.Instancer.IServerConfigurationAnalyzer.html","topicHref":"Coree.NETASP.Services.Instancer.IServerConfigurationAnalyzer.html","topicUid":"Coree.NETASP.Services.Instancer.IServerConfigurationAnalyzer"},{"name":"ServerConfigurationAnalyzer","href":"Coree.NETASP.Services.Instancer.ServerConfigurationAnalyzer.html","topicHref":"Coree.NETASP.Services.Instancer.ServerConfigurationAnalyzer.html","topicUid":"Coree.NETASP.Services.Instancer.ServerConfigurationAnalyzer"},{"name":"ServerConfigurationAnalyzer.ServerListenDetail","href":"Coree.NETASP.Services.Instancer.ServerConfigurationAnalyzer.ServerListenDetail.html","topicHref":"Coree.NETASP.Services.Instancer.ServerConfigurationAnalyzer.ServerListenDetail.html","topicUid":"Coree.NETASP.Services.Instancer.ServerConfigurationAnalyzer.ServerListenDetail"}]},{"name":"Coree.NETASP.Services.Points","href":"Coree.NETASP.Services.Points.html","topicHref":"Coree.NETASP.Services.Points.html","topicUid":"Coree.NETASP.Services.Points","items":[{"name":"Entry","href":"Coree.NETASP.Services.Points.Entry.html","topicHref":"Coree.NETASP.Services.Points.Entry.html","topicUid":"Coree.NETASP.Services.Points.Entry"},{"name":"IPointService","href":"Coree.NETASP.Services.Points.IPointService.html","topicHref":"Coree.NETASP.Services.Points.IPointService.html","topicUid":"Coree.NETASP.Services.Points.IPointService"},{"name":"PointEntry","href":"Coree.NETASP.Services.Points.PointEntry.html","topicHref":"Coree.NETASP.Services.Points.PointEntry.html","topicUid":"Coree.NETASP.Services.Points.PointEntry"},{"name":"PointService","href":"Coree.NETASP.Services.Points.PointService.html","topicHref":"Coree.NETASP.Services.Points.PointService.html","topicUid":"Coree.NETASP.Services.Points.PointService"},{"name":"PointServiceOptions","href":"Coree.NETASP.Services.Points.PointServiceOptions.html","topicHref":"Coree.NETASP.Services.Points.PointServiceOptions.html","topicUid":"Coree.NETASP.Services.Points.PointServiceOptions"}]},{"name":"Coree.NETASP.UnderConstruction","href":"Coree.NETASP.UnderConstruction.html","topicHref":"Coree.NETASP.UnderConstruction.html","topicUid":"Coree.NETASP.UnderConstruction","items":[{"name":"CustomWebApplication","href":"Coree.NETASP.UnderConstruction.CustomWebApplication.html","topicHref":"Coree.NETASP.UnderConstruction.CustomWebApplication.html","topicUid":"Coree.NETASP.UnderConstruction.CustomWebApplication"},{"name":"CustomWebApplication2","href":"Coree.NETASP.UnderConstruction.CustomWebApplication2.html","topicHref":"Coree.NETASP.UnderConstruction.CustomWebApplication2.html","topicUid":"Coree.NETASP.UnderConstruction.CustomWebApplication2"},{"name":"DummyFileProvider","href":"Coree.NETASP.UnderConstruction.DummyFileProvider.html","topicHref":"Coree.NETASP.UnderConstruction.DummyFileProvider.html","topicUid":"Coree.NETASP.UnderConstruction.DummyFileProvider"},{"name":"EmptyWebHostBuilder","href":"Coree.NETASP.UnderConstruction.EmptyWebHostBuilder.html","topicHref":"Coree.NETASP.UnderConstruction.EmptyWebHostBuilder.html","topicUid":"Coree.NETASP.UnderConstruction.EmptyWebHostBuilder"},{"name":"EmptyWebHostBuilder2","href":"Coree.NETASP.UnderConstruction.EmptyWebHostBuilder2.html","topicHref":"Coree.NETASP.UnderConstruction.EmptyWebHostBuilder2.html","topicUid":"Coree.NETASP.UnderConstruction.EmptyWebHostBuilder2"},{"name":"EmptyWebHostBuilder3","href":"Coree.NETASP.UnderConstruction.EmptyWebHostBuilder3.html","topicHref":"Coree.NETASP.UnderConstruction.EmptyWebHostBuilder3.html","topicUid":"Coree.NETASP.UnderConstruction.EmptyWebHostBuilder3"},{"name":"EmptyWebHostBuilderx","href":"Coree.NETASP.UnderConstruction.EmptyWebHostBuilderx.html","topicHref":"Coree.NETASP.UnderConstruction.EmptyWebHostBuilderx.html","topicUid":"Coree.NETASP.UnderConstruction.EmptyWebHostBuilderx"},{"name":"ExampleClass","href":"Coree.NETASP.UnderConstruction.ExampleClass.html","topicHref":"Coree.NETASP.UnderConstruction.ExampleClass.html","topicUid":"Coree.NETASP.UnderConstruction.ExampleClass"},{"name":"FileServerMiddleware","href":"Coree.NETASP.UnderConstruction.FileServerMiddleware.html","topicHref":"Coree.NETASP.UnderConstruction.FileServerMiddleware.html","topicUid":"Coree.NETASP.UnderConstruction.FileServerMiddleware"},{"name":"FileServerMiddlewareExtensions","href":"Coree.NETASP.UnderConstruction.FileServerMiddlewareExtensions.html","topicHref":"Coree.NETASP.UnderConstruction.FileServerMiddlewareExtensions.html","topicUid":"Coree.NETASP.UnderConstruction.FileServerMiddlewareExtensions"},{"name":"MyWebHostBuilder","href":"Coree.NETASP.UnderConstruction.MyWebHostBuilder.html","topicHref":"Coree.NETASP.UnderConstruction.MyWebHostBuilder.html","topicUid":"Coree.NETASP.UnderConstruction.MyWebHostBuilder"},{"name":"ObjectDumper","href":"Coree.NETASP.UnderConstruction.ObjectDumper.html","topicHref":"Coree.NETASP.UnderConstruction.ObjectDumper.html","topicUid":"Coree.NETASP.UnderConstruction.ObjectDumper"},{"name":"ObjectDumper2","href":"Coree.NETASP.UnderConstruction.ObjectDumper2.html","topicHref":"Coree.NETASP.UnderConstruction.ObjectDumper2.html","topicUid":"Coree.NETASP.UnderConstruction.ObjectDumper2"},{"name":"ObjectDumper3","href":"Coree.NETASP.UnderConstruction.ObjectDumper3.html","topicHref":"Coree.NETASP.UnderConstruction.ObjectDumper3.html","topicUid":"Coree.NETASP.UnderConstruction.ObjectDumper3"},{"name":"OptionsDumper","href":"Coree.NETASP.UnderConstruction.OptionsDumper.html","topicHref":"Coree.NETASP.UnderConstruction.OptionsDumper.html","topicUid":"Coree.NETASP.UnderConstruction.OptionsDumper"},{"name":"OptionsKestrelServerOptionsExtensions","href":"Coree.NETASP.UnderConstruction.OptionsKestrelServerOptionsExtensions.html","topicHref":"Coree.NETASP.UnderConstruction.OptionsKestrelServerOptionsExtensions.html","topicUid":"Coree.NETASP.UnderConstruction.OptionsKestrelServerOptionsExtensions"},{"name":"PhpCgiExecutor","href":"Coree.NETASP.UnderConstruction.PhpCgiExecutor.html","topicHref":"Coree.NETASP.UnderConstruction.PhpCgiExecutor.html","topicUid":"Coree.NETASP.UnderConstruction.PhpCgiExecutor"},{"name":"Product","href":"Coree.NETASP.UnderConstruction.Product.html","topicHref":"Coree.NETASP.UnderConstruction.Product.html","topicUid":"Coree.NETASP.UnderConstruction.Product"},{"name":"PropertyAccessTracker<T>","href":"Coree.NETASP.UnderConstruction.PropertyAccessTracker-1.html","topicHref":"Coree.NETASP.UnderConstruction.PropertyAccessTracker-1.html","topicUid":"Coree.NETASP.UnderConstruction.PropertyAccessTracker`1","name.vb":"PropertyAccessTracker(Of T)"},{"name":"ServicesDumper","href":"Coree.NETASP.UnderConstruction.ServicesDumper.html","topicHref":"Coree.NETASP.UnderConstruction.ServicesDumper.html","topicUid":"Coree.NETASP.UnderConstruction.ServicesDumper"},{"name":"TrackableItem<T>","href":"Coree.NETASP.UnderConstruction.TrackableItem-1.html","topicHref":"Coree.NETASP.UnderConstruction.TrackableItem-1.html","topicUid":"Coree.NETASP.UnderConstruction.TrackableItem`1","name.vb":"TrackableItem(Of T)"},{"name":"TrackableList<T>","href":"Coree.NETASP.UnderConstruction.TrackableList-1.html","topicHref":"Coree.NETASP.UnderConstruction.TrackableList-1.html","topicUid":"Coree.NETASP.UnderConstruction.TrackableList`1","name.vb":"TrackableList(Of T)"},{"name":"TrackableState","href":"Coree.NETASP.UnderConstruction.TrackableState.html","topicHref":"Coree.NETASP.UnderConstruction.TrackableState.html","topicUid":"Coree.NETASP.UnderConstruction.TrackableState"}]}],"memberLayout":"SamePage"}
